arkosctl/__init__.py
arkosctl/logs.py
arkosctl/utils.py
arkosctl/frameworks/__init__.py
arkosctl/frameworks/apikeys.py
arkosctl/frameworks/applications.py
arkosctl/frameworks/backups.py
arkosctl/frameworks/certificates.py
arkosctl/frameworks/databases.py
arkosctl/frameworks/files.py
arkosctl/frameworks/filesystems.py
arkosctl/frameworks/networks.py
arkosctl/frameworks/packages.py
arkosctl/frameworks/roles.py
arkosctl/frameworks/security.py
arkosctl/frameworks/services.py
arkosctl/frameworks/system.py
arkosctl/frameworks/websites.py
arkosctl-0.3.dist-info/DESCRIPTION.rst
arkosctl-0.3.dist-info/METADATA
arkosctl-0.3.dist-info/RECORD
arkosctl-0.3.dist-info/WHEEL
arkosctl-0.3.dist-info/entry_points.txt
arkosctl-0.3.dist-info/metadata.json
arkosctl-0.3.dist-info/top_level.txt
